mlite/__init__.py
mlite/regression.py
mlite-0.0.2.dist-info/METADATA
mlite-0.0.2.dist-info/WHEEL
mlite-0.0.2.dist-info/top_level.txt
mlite-0.0.2.dist-info/RECORD
