Metadata-Version: 2.1
Name: mlite
Version: 0.0.2
Summary: A lightweight machine learning library with linear regression functionality
Author: Suraj Kumar Sharma
Author-email: surajksharma2304@gmail.com
License: MIT
Classifier: Programming Language :: Python :: 3
Classifier: License :: OSI Approved :: MIT License
Classifier: Operating System :: OS Independent
Requires-Python: >=3.6
Requires-Dist: numpy
